nonebot/adapters/telegram/__init__.py
nonebot/adapters/telegram/adapter.py
nonebot/adapters/telegram/bot.py
nonebot/adapters/telegram/cache.py
nonebot/adapters/telegram/config.py
nonebot/adapters/telegram/event.py
nonebot/adapters/telegram/exception.py
nonebot/adapters/telegram/menu_helper.py
nonebot/adapters/telegram/message.py
nonebot/adapters/telegram/models.py
nonebot/adapters/telegram/utils.py
nonebot_adapter_antelegram-0.2.0.dev12.dist-info/WHEEL
nonebot_adapter_antelegram-0.2.0.dev12.dist-info/LICENSE
nonebot_adapter_antelegram-0.2.0.dev12.dist-info/METADATA
nonebot_adapter_antelegram-0.2.0.dev12.dist-info/RECORD
