Metadata-Version: 2.1
Name: nonebot-adapter-antelegram
Version: 0.2.0.dev12
Summary: Another unofficial Telegram adapter for nonebot2
Home-page: https://github.com/ColdThunder11/nonebot-adapter-telegram
License: MIT
Keywords: bot,telegram
Author: ColdThunder11
Author-email: lslyj27761@gmail.com
Requires-Python: >=3.8.1,<4.0.0
Classifier: Framework :: Robot Framework
Classifier: Framework :: Robot Framework :: Library
Classifier: License :: OSI Approved :: MIT License
Classifier: Operating System :: OS Independent
Classifier: Programming Language :: Python :: 3
Classifier: Programming Language :: Python :: 3.9
Classifier: Programming Language :: Python :: 3.10
Classifier: Programming Language :: Python :: 3.11
Classifier: Programming Language :: Python :: 3
Requires-Dist: aiocache (>=0.11.1,<0.12.0)
Requires-Dist: httpx[http2] (>=0.20.0,<1.0.0)
Requires-Dist: nonebot2 (>=2.0.0rc2,<3.0.0)
Requires-Dist: redis (>=4.2.0rc1)
Project-URL: Repository, https://github.com/ColdThunder11/nonebot-adapter-telegram
